marv_ludwig/__init__.py
marv_ludwig/static/index.html
marv_ludwig/static/main-built.css
marv_ludwig/static/main-built.js
marv_ludwig/static/manifest.json
marv_ludwig/static/sw.js
marv_ludwig/static/app/styles/fonts/SourceSansPro-It.otf.woff
marv_ludwig/static/app/styles/fonts/SourceSansPro-It.ttf.woff2
marv_ludwig/static/app/styles/fonts/SourceSansPro-Light.otf.woff
marv_ludwig/static/app/styles/fonts/SourceSansPro-Light.ttf.woff2
marv_ludwig/static/app/styles/fonts/SourceSansPro-LightIt.otf.woff
marv_ludwig/static/app/styles/fonts/SourceSansPro-LightIt.ttf.woff2
marv_ludwig/static/app/styles/fonts/SourceSansPro-Regular.otf.woff
marv_ludwig/static/app/styles/fonts/SourceSansPro-Regular.ttf.woff2
marv_ludwig/static/app/styles/icons/calendar.svg
marv_ludwig/static/app/styles/icons/check.svg
marv_ludwig/static/app/styles/icons/chevron-left.svg
marv_ludwig/static/app/styles/icons/chevron-right.svg
marv_ludwig/static/app/styles/icons/clipboard.svg
marv_ludwig/static/app/styles/icons/clock.svg
marv_ludwig/static/app/styles/icons/cloud-upload.svg
marv_ludwig/static/app/styles/icons/cog.svg
marv_ludwig/static/app/styles/icons/dashboard.svg
marv_ludwig/static/app/styles/icons/eye.svg
marv_ludwig/static/app/styles/icons/fullscreen-enter.svg
marv_ludwig/static/app/styles/icons/fullscreen-exit.svg
marv_ludwig/static/app/styles/icons/globe.svg
marv_ludwig/static/app/styles/icons/info.svg
marv_ludwig/static/app/styles/icons/list-rich.svg
marv_ludwig/static/app/styles/icons/list.svg
marv_ludwig/static/app/styles/icons/lock-locked.svg
marv_ludwig/static/app/styles/icons/media-pause.svg
marv_ludwig/static/app/styles/icons/media-play.svg
marv_ludwig/static/app/styles/icons/media-record.svg
marv_ludwig/static/app/styles/icons/media-skip-backward.svg
marv_ludwig/static/app/styles/icons/media-skip-forward.svg
marv_ludwig/static/app/styles/icons/media-step-backward.svg
marv_ludwig/static/app/styles/icons/media-step-forward.svg
marv_ludwig/static/app/styles/icons/media-stop.svg
marv_ludwig-20.8.0.dist-info/LICENSE.txt
marv_ludwig-20.8.0.dist-info/METADATA
marv_ludwig-20.8.0.dist-info/WHEEL
marv_ludwig-20.8.0.dist-info/top_level.txt
marv_ludwig-20.8.0.dist-info/RECORD
