Metadata-Version: 2.1
Name: marv-ludwig
Version: 20.8.0
Summary: MARV Robotics web frontend bundle
Home-page: https://ternaris.com/marv-robotics
Author: Ternaris
Author-email: team@ternaris.com
Maintainer: Ternaris
Maintainer-email: team@ternaris.com
License: AGPL-3.0-only
Project-URL: Documentation, https://ternaris.com/marv-robotics/docs/
Project-URL: Code, https://gitlab.com/ternaris/marv-robotics
Project-URL: Issue tracker, https://gitlab.com/ternaris/marv-robotics/issues
Platform: UNKNOWN
Classifier: Development Status :: 5 - Production/Stable
Classifier: License :: OSI Approved :: GNU Affero General Public License v3
Classifier: Operating System :: POSIX :: Linux
Classifier: Programming Language :: Python :: 3 :: Only
Classifier: Programming Language :: Python :: 3.7
Classifier: Programming Language :: Python :: 3.8
Classifier: Programming Language :: Python :: Implementation :: CPython
Classifier: Programming Language :: Python
Classifier: Topic :: Scientific/Engineering
Requires-Python: >=3.7.1
